qbitnum/__init__.py
qbitnum/qbitnum.py
qbitnum/tests/__init__.py
qbitnum/tests/test_qbitnum.py
qbitnum-0.1.3.dist-info/METADATA
qbitnum-0.1.3.dist-info/WHEEL
qbitnum-0.1.3.dist-info/top_level.txt
qbitnum-0.1.3.dist-info/RECORD
