Metadata-Version: 2.4
Name: qbitnum
Version: 0.1.3
Summary: Quantum‐inspired numeric data type for probabilistic arithmetic
Home-page: https://github.com/catchmaurya/qbitnum
Author: Maurya Allimuthu
Author-email: catchmaurya@gmail.com
License: MIT
Keywords: quantum qubit probabilistic arithmetic
Classifier: Programming Language :: Python :: 3
Classifier: License :: OSI Approved :: MIT License
Classifier: Topic :: Scientific/Engineering :: Mathematics
Requires-Python: >=3.7
Dynamic: author
Dynamic: author-email
Dynamic: classifier
Dynamic: description
Dynamic: description-content-type
Dynamic: home-page
Dynamic: keywords
Dynamic: license
Dynamic: requires-python
Dynamic: summary
